jijzeptlab_themes/__init__.py
jijzeptlab_themes/_version.py
jijzeptlab_themes/labextension/package.json
jijzeptlab_themes/labextension/schemas/jijzeptlab_themes/package.json.orig
jijzeptlab_themes/labextension/schemas/jijzeptlab_themes/plugin.json
jijzeptlab_themes/labextension/static/114.95c1ee11bc3b4dac7ead.js
jijzeptlab_themes/labextension/static/353.f8a589d7fbb2e3cfbd75.js
jijzeptlab_themes/labextension/static/remoteEntry.b24e0486442b6c6282f9.js
jijzeptlab_themes/labextension/static/style.js
jijzeptlab_themes/labextension/static/third-party-licenses.json
jijzeptlab_themes/labextension/themes/jijzeptlab_themes/index.css
jijzeptlab_themes/labextension/themes/jijzeptlab_themes/index.js
jijzeptlab_themes-0.2.3.data/data/share/jupyter/labextensions/jijzeptlab_themes/package.json
jijzeptlab_themes-0.2.3.data/data/share/jupyter/labextensions/jijzeptlab_themes/schemas/jijzeptlab_themes/package.json.orig
jijzeptlab_themes-0.2.3.data/data/share/jupyter/labextensions/jijzeptlab_themes/schemas/jijzeptlab_themes/plugin.json
jijzeptlab_themes-0.2.3.data/data/share/jupyter/labextensions/jijzeptlab_themes/static/114.95c1ee11bc3b4dac7ead.js
jijzeptlab_themes-0.2.3.data/data/share/jupyter/labextensions/jijzeptlab_themes/static/353.f8a589d7fbb2e3cfbd75.js
jijzeptlab_themes-0.2.3.data/data/share/jupyter/labextensions/jijzeptlab_themes/static/remoteEntry.b24e0486442b6c6282f9.js
jijzeptlab_themes-0.2.3.data/data/share/jupyter/labextensions/jijzeptlab_themes/static/style.js
jijzeptlab_themes-0.2.3.data/data/share/jupyter/labextensions/jijzeptlab_themes/static/third-party-licenses.json
jijzeptlab_themes-0.2.3.data/data/share/jupyter/labextensions/jijzeptlab_themes/themes/jijzeptlab_themes/index.css
jijzeptlab_themes-0.2.3.data/data/share/jupyter/labextensions/jijzeptlab_themes/themes/jijzeptlab_themes/index.js
jijzeptlab_themes-0.2.3.data/data/share/jupyter/labextensions/jijzeptlab_themes/install.json
jijzeptlab_themes-0.2.3.dist-info/METADATA
jijzeptlab_themes-0.2.3.dist-info/WHEEL
jijzeptlab_themes-0.2.3.dist-info/licenses/LICENSE
jijzeptlab_themes-0.2.3.dist-info/RECORD
